qreservoir/__init__.py
qreservoir/abstract_base_classes.py
qreservoir/datasets.py
qreservoir/encoders.py
qreservoir/models.py
qreservoir/reservoirs.py
qreservoir-0.5.0.dist-info/LICENSE
qreservoir-0.5.0.dist-info/METADATA
qreservoir-0.5.0.dist-info/WHEEL
qreservoir-0.5.0.dist-info/RECORD
