Metadata-Version: 2.1
Name: qreservoir
Version: 0.5.0
Summary: Python package for quantum reservoir computing using Qulacs
Home-page: https://github.com/owenagnel/qreservoir
License: MIT
Author: Owen Agnel
Author-email: owen.agnel@gmail.com
Requires-Python: >=3.10,<3.12
Classifier: License :: OSI Approved :: MIT License
Classifier: Programming Language :: Python :: 3
Classifier: Programming Language :: Python :: 3.10
Classifier: Programming Language :: Python :: 3.11
Requires-Dist: colour (>=0.1.5,<0.2.0)
Requires-Dist: matplotlib (>=3.7.2,<4.0.0)
Requires-Dist: qulacs (>=0.6.1,<0.7.0)
Requires-Dist: qulacsvis (>=0.7.3,<0.8.0)
Requires-Dist: scikit-learn (>=1.3.0,<2.0.0)
Project-URL: Repository, https://github.com/owenagnel/qreservoir
